<stg><name>get_centroid_fh_Bloc.1</name>


<trans_list>
</trans_list>



<state_list>

<state id="1" st_id="1">

<operation id="2" st_id="1" stage="1" lat="1">
<core>NULL</core>
<MemPortIdVec></MemPortIdVec>
<condition id="-1">
<or_exp><and_exp></and_exp></or_exp>
</condition>

<Node id="3" bw="0" op_0_bw="0" op_1_bw="16" op_2_bw="0" op_3_bw="32" op_4_bw="32" op_5_bw="0" op_6_bw="32" op_7_bw="32" op_8_bw="0" op_9_bw="0" op_10_bw="0" op_11_bw="32" op_12_bw="32" op_13_bw="32" op_14_bw="32" op_15_bw="0" op_16_bw="0">
<![CDATA[
entry:0  call void (...)* @_ssdm_op_SpecInterface(i16* %h_limit, [8 x i8]* @ap_fifo_str, i32 0, i32 0, [1 x i8]* @p_str, i32 0, i32 0, [1 x i8]* @p_str, [1 x i8]* @p_str, [1 x i8]* @p_str, i32 2, i32 2, i32 16, i32 16, [1 x i8]* @p_str, [11 x i8]* @ScalarProp_str)

]]></Node>
<StgValue><ssdm name="specinterface_ln0"/></StgValue>
</operation>

<operation id="3" st_id="1" stage="1" lat="1">
<core>NULL</core>
<MemPortIdVec></MemPortIdVec>
<condition id="-1">
<or_exp><and_exp></and_exp></or_exp>
</condition>

<Node id="4" bw="0" op_0_bw="0" op_1_bw="8" op_2_bw="0" op_3_bw="32" op_4_bw="32" op_5_bw="0" op_6_bw="32" op_7_bw="32" op_8_bw="0" op_9_bw="0" op_10_bw="0" op_11_bw="32" op_12_bw="32" op_13_bw="32" op_14_bw="32" op_15_bw="0" op_16_bw="0">
<![CDATA[
entry:1  call void (...)* @_ssdm_op_SpecInterface(i8* %v_limit, [8 x i8]* @ap_fifo_str, i32 0, i32 0, [1 x i8]* @p_str, i32 0, i32 0, [1 x i8]* @p_str, [1 x i8]* @p_str, [1 x i8]* @p_str, i32 2, i32 2, i32 16, i32 16, [1 x i8]* @p_str, [11 x i8]* @ScalarProp_str)

]]></Node>
<StgValue><ssdm name="specinterface_ln0"/></StgValue>
</operation>

<operation id="4" st_id="1" stage="1" lat="1">
<core>FIFO</core>
<MemPortIdVec></MemPortIdVec>
<condition id="-1">
<or_exp><and_exp></and_exp></or_exp>
</condition>

<Node id="5" bw="8" op_0_bw="8" op_1_bw="8">
<![CDATA[
entry:2  %v_limit_read = call i8 @_ssdm_op_Read.ap_fifo.i8P(i8* %v_limit)

]]></Node>
<StgValue><ssdm name="v_limit_read"/></StgValue>
</operation>

<operation id="5" st_id="1" stage="1" lat="1">
<core>FIFO</core>
<MemPortIdVec></MemPortIdVec>
<condition id="-1">
<or_exp><and_exp></and_exp></or_exp>
</condition>

<Node id="6" bw="16" op_0_bw="16" op_1_bw="16">
<![CDATA[
entry:3  %h_limit_read = call i16 @_ssdm_op_Read.ap_fifo.i16P(i16* %h_limit)

]]></Node>
<StgValue><ssdm name="h_limit_read"/></StgValue>
</operation>

<operation id="6" st_id="1" stage="1" lat="1">
<core>NULL</core>
<MemPortIdVec></MemPortIdVec>
<condition id="-1">
<or_exp><and_exp></and_exp></or_exp>
</condition>

<Node id="7" bw="7" op_0_bw="7" op_1_bw="8" op_2_bw="32" op_3_bw="32">
<![CDATA[
entry:4  %lshr_ln = call i7 @_ssdm_op_PartSelect.i7.i8.i32.i32(i8 %v_limit_read, i32 1, i32 7)

]]></Node>
<StgValue><ssdm name="lshr_ln"/></StgValue>
</operation>

<operation id="7" st_id="1" stage="1" lat="1">
<core>NULL</core>
<MemPortIdVec></MemPortIdVec>
<condition id="-1">
<or_exp><and_exp></and_exp></or_exp>
</condition>

<Node id="8" bw="16" op_0_bw="7">
<![CDATA[
entry:5  %zext_ln146 = zext i7 %lshr_ln to i16

]]></Node>
<StgValue><ssdm name="zext_ln146"/></StgValue>
</operation>

<operation id="8" st_id="1" stage="1" lat="1">
<core>NULL</core>
<MemPortIdVec></MemPortIdVec>
<condition id="-1">
<or_exp><and_exp></and_exp></or_exp>
</condition>

<Node id="9" bw="15" op_0_bw="15" op_1_bw="16" op_2_bw="32" op_3_bw="32">
<![CDATA[
entry:6  %lshr_ln1 = call i15 @_ssdm_op_PartSelect.i15.i16.i32.i32(i16 %h_limit_read, i32 1, i32 15)

]]></Node>
<StgValue><ssdm name="lshr_ln1"/></StgValue>
</operation>

<operation id="9" st_id="1" stage="1" lat="1">
<core>NULL</core>
<MemPortIdVec></MemPortIdVec>
<condition id="-1">
<or_exp><and_exp></and_exp></or_exp>
</condition>

<Node id="10" bw="32" op_0_bw="15">
<![CDATA[
entry:7  %zext_ln147 = zext i15 %lshr_ln1 to i32

]]></Node>
<StgValue><ssdm name="zext_ln147"/></StgValue>
</operation>

<operation id="10" st_id="1" stage="1" lat="1">
<core>NULL</core>
<MemPortIdVec></MemPortIdVec>
<condition id="-1">
<or_exp><and_exp></and_exp></or_exp>
</condition>

<Node id="11" bw="48" op_0_bw="48" op_1_bw="16">
<![CDATA[
entry:8  %mrv = insertvalue { i16, i32 } undef, i16 %zext_ln146, 0

]]></Node>
<StgValue><ssdm name="mrv"/></StgValue>
</operation>

<operation id="11" st_id="1" stage="1" lat="1">
<core>NULL</core>
<MemPortIdVec></MemPortIdVec>
<condition id="-1">
<or_exp><and_exp></and_exp></or_exp>
</condition>

<Node id="12" bw="48" op_0_bw="48" op_1_bw="32">
<![CDATA[
entry:9  %mrv_1 = insertvalue { i16, i32 } %mrv, i32 %zext_ln147, 1

]]></Node>
<StgValue><ssdm name="mrv_1"/></StgValue>
</operation>

<operation id="12" st_id="1" stage="1" lat="1">
<core>NULL</core>
<MemPortIdVec></MemPortIdVec>
<condition id="-1">
<or_exp><and_exp></and_exp></or_exp>
</condition>

<Node id="13" bw="0" op_0_bw="48">
<![CDATA[
entry:10  ret { i16, i32 } %mrv_1

]]></Node>
<StgValue><ssdm name="ret_ln142"/></StgValue>
</operation>
</state>
</state_list>


<ports>
<port id="13" name="v_limit" dir="0" iftype="3">
<core>FIFO</core><StgValue><ssdm name="v_limit"/></StgValue>
</port>
<port id="14" name="h_limit" dir="0" iftype="3">
<core>FIFO</core><StgValue><ssdm name="h_limit"/></StgValue>
</port>
</ports>


<dataflows>
<dataflow id="16" from="_ssdm_op_SpecInterface" to="specinterface_ln0" fromId="15" toId="2">
</dataflow>
<dataflow id="17" from="h_limit" to="specinterface_ln0" fromId="14" toId="2">
</dataflow>
<dataflow id="19" from="ap_fifo_str" to="specinterface_ln0" fromId="18" toId="2">
</dataflow>
<dataflow id="21" from="StgValue_20" to="specinterface_ln0" fromId="20" toId="2">
</dataflow>
<dataflow id="22" from="StgValue_20" to="specinterface_ln0" fromId="20" toId="2">
</dataflow>
<dataflow id="24" from="p_str" to="specinterface_ln0" fromId="23" toId="2">
</dataflow>
<dataflow id="25" from="StgValue_20" to="specinterface_ln0" fromId="20" toId="2">
</dataflow>
<dataflow id="26" from="StgValue_20" to="specinterface_ln0" fromId="20" toId="2">
</dataflow>
<dataflow id="27" from="p_str" to="specinterface_ln0" fromId="23" toId="2">
</dataflow>
<dataflow id="28" from="p_str" to="specinterface_ln0" fromId="23" toId="2">
</dataflow>
<dataflow id="29" from="p_str" to="specinterface_ln0" fromId="23" toId="2">
</dataflow>
<dataflow id="31" from="StgValue_30" to="specinterface_ln0" fromId="30" toId="2">
</dataflow>
<dataflow id="32" from="StgValue_30" to="specinterface_ln0" fromId="30" toId="2">
</dataflow>
<dataflow id="34" from="StgValue_33" to="specinterface_ln0" fromId="33" toId="2">
</dataflow>
<dataflow id="35" from="StgValue_33" to="specinterface_ln0" fromId="33" toId="2">
</dataflow>
<dataflow id="36" from="p_str" to="specinterface_ln0" fromId="23" toId="2">
</dataflow>
<dataflow id="38" from="ScalarProp_str" to="specinterface_ln0" fromId="37" toId="2">
</dataflow>
<dataflow id="39" from="_ssdm_op_SpecInterface" to="specinterface_ln0" fromId="15" toId="3">
</dataflow>
<dataflow id="40" from="v_limit" to="specinterface_ln0" fromId="13" toId="3">
</dataflow>
<dataflow id="41" from="ap_fifo_str" to="specinterface_ln0" fromId="18" toId="3">
</dataflow>
<dataflow id="42" from="StgValue_20" to="specinterface_ln0" fromId="20" toId="3">
</dataflow>
<dataflow id="43" from="StgValue_20" to="specinterface_ln0" fromId="20" toId="3">
</dataflow>
<dataflow id="44" from="p_str" to="specinterface_ln0" fromId="23" toId="3">
</dataflow>
<dataflow id="45" from="StgValue_20" to="specinterface_ln0" fromId="20" toId="3">
</dataflow>
<dataflow id="46" from="StgValue_20" to="specinterface_ln0" fromId="20" toId="3">
</dataflow>
<dataflow id="47" from="p_str" to="specinterface_ln0" fromId="23" toId="3">
</dataflow>
<dataflow id="48" from="p_str" to="specinterface_ln0" fromId="23" toId="3">
</dataflow>
<dataflow id="49" from="p_str" to="specinterface_ln0" fromId="23" toId="3">
</dataflow>
<dataflow id="50" from="StgValue_30" to="specinterface_ln0" fromId="30" toId="3">
</dataflow>
<dataflow id="51" from="StgValue_30" to="specinterface_ln0" fromId="30" toId="3">
</dataflow>
<dataflow id="52" from="StgValue_33" to="specinterface_ln0" fromId="33" toId="3">
</dataflow>
<dataflow id="53" from="StgValue_33" to="specinterface_ln0" fromId="33" toId="3">
</dataflow>
<dataflow id="54" from="p_str" to="specinterface_ln0" fromId="23" toId="3">
</dataflow>
<dataflow id="55" from="ScalarProp_str" to="specinterface_ln0" fromId="37" toId="3">
</dataflow>
<dataflow id="57" from="_ssdm_op_Read.ap_fifo.i8P" to="v_limit_read" fromId="56" toId="4">
</dataflow>
<dataflow id="58" from="v_limit" to="v_limit_read" fromId="13" toId="4">
</dataflow>
<dataflow id="60" from="_ssdm_op_Read.ap_fifo.i16P" to="h_limit_read" fromId="59" toId="5">
</dataflow>
<dataflow id="61" from="h_limit" to="h_limit_read" fromId="14" toId="5">
</dataflow>
<dataflow id="63" from="_ssdm_op_PartSelect.i7.i8.i32.i32" to="lshr_ln" fromId="62" toId="6">
</dataflow>
<dataflow id="64" from="v_limit_read" to="lshr_ln" fromId="4" toId="6">
</dataflow>
<dataflow id="66" from="StgValue_65" to="lshr_ln" fromId="65" toId="6">
</dataflow>
<dataflow id="68" from="StgValue_67" to="lshr_ln" fromId="67" toId="6">
</dataflow>
<dataflow id="69" from="lshr_ln" to="zext_ln146" fromId="6" toId="7">
</dataflow>
<dataflow id="71" from="_ssdm_op_PartSelect.i15.i16.i32.i32" to="lshr_ln1" fromId="70" toId="8">
</dataflow>
<dataflow id="72" from="h_limit_read" to="lshr_ln1" fromId="5" toId="8">
</dataflow>
<dataflow id="73" from="StgValue_65" to="lshr_ln1" fromId="65" toId="8">
</dataflow>
<dataflow id="75" from="StgValue_74" to="lshr_ln1" fromId="74" toId="8">
</dataflow>
<dataflow id="76" from="lshr_ln1" to="zext_ln147" fromId="8" toId="9">
</dataflow>
<dataflow id="78" from="StgValue_77" to="mrv" fromId="77" toId="10">
</dataflow>
<dataflow id="79" from="zext_ln146" to="mrv" fromId="7" toId="10">
</dataflow>
<dataflow id="80" from="mrv" to="mrv_1" fromId="10" toId="11">
</dataflow>
<dataflow id="81" from="zext_ln147" to="mrv_1" fromId="9" toId="11">
</dataflow>
<dataflow id="82" from="mrv_1" to="ret_ln142" fromId="11" toId="12">
</dataflow>
</dataflows>


</stg>
